db2db/__init__.py
db2db/core.py
db2db/transfer.py
db2db/utils.py
dbtodb/__init__.py
dbtodb/core.py
dbtodb/transfer.py
dbtodb/utils.py
tests/__init__.py
db2db_2-0.1.0.dist-info/LICENSE
db2db_2-0.1.0.dist-info/METADATA
db2db_2-0.1.0.dist-info/WHEEL
db2db_2-0.1.0.dist-info/top_level.txt
db2db_2-0.1.0.dist-info/RECORD
