Metadata-Version: 2.1
Name: db2db-2
Version: 0.1.0
Summary: A package to transfer data between SQL databases like PostgreSQL, MySQL, MSSQL.
Home-page: https://github.com/Akhtar21yr/db2db
Author: Akhtar Raza
Author-email: akhtar.decy@gmail.com
Classifier: Programming Language :: Python :: 3
Classifier: License :: OSI Approved :: MIT License
Classifier: Operating System :: OS Independent
Requires-Python: >=3.7
License-File: LICENSE
Requires-Dist: pandas>=1.3.0
Requires-Dist: SQLAlchemy>=1.4.0
Requires-Dist: psycopg2-binary>=2.9.0
Requires-Dist: mysql-connector-python>=8.0.0
Requires-Dist: pyodbc>=4.0.0
